OpenLA/__init__.py
OpenLA/check.py
OpenLA/course_information.py
OpenLA/data_classes/event_stream.py
OpenLA/data_classes/operation_count.py
OpenLA/data_classes/pagewise_aggregation.py
OpenLA/data_classes/time_range_aggregation.py
OpenLA/data_conversion.py
OpenLA/data_extraction.py
OpenLA/data_visualization.py
openla-0.3.0.dist-info/LICENSE
openla-0.3.0.dist-info/METADATA
openla-0.3.0.dist-info/WHEEL
openla-0.3.0.dist-info/RECORD
