Metadata-Version: 2.1
Name: openla
Version: 0.3.0
Summary: Open source library for e-Book log analysis
License: MIT
Author: LIMU
Author-email: repository@limu.ait.kyushu-u.ac.jp
Requires-Python: >=3.7.1,<4.0
Classifier: License :: OSI Approved :: MIT License
Classifier: Programming Language :: Python :: 3
Classifier: Programming Language :: Python :: 3.8
Classifier: Programming Language :: Python :: 3.9
Classifier: Programming Language :: Python :: 3.10
Classifier: Programming Language :: Python :: 3.11
Requires-Dist: matplotlib (>=3.3.2,<4.0.0)
Requires-Dist: numpy (>=1.18.15,<2.0.0)
Requires-Dist: pandas (>=1.3,<2.0)
